pddlpy/__init__.py
pddlpy/pddl.py
pddlpy/pddlLexer.py
pddlpy/pddlListener.py
pddlpy/pddlParser.py
planning_sat/__init__.py
planning_sat/davis_putnam.py
planning_sat/dpll.py
planning_sat/encoder.py
planning_sat/pddl_adapter.py
tests/__init__.py
tests/test_davis_putnam.py
tests/test_dpll.py
tests/test_encoder.py
tests/test_pddl_adapter.py
planning_sat-0.0.2.dist-info/LICENSE
planning_sat-0.0.2.dist-info/METADATA
planning_sat-0.0.2.dist-info/WHEEL
planning_sat-0.0.2.dist-info/top_level.txt
planning_sat-0.0.2.dist-info/RECORD
